singstat/__init__.py
singstat/client.py
singstat/constants.py
singstat/exceptions.py
singstat/py.typed
singstat/singstat.py
singstat/timezone.py
singstat/types.py
singstat/types_args.py
singstat-2.0.2.dist-info/LICENSE.txt
singstat-2.0.2.dist-info/METADATA
singstat-2.0.2.dist-info/WHEEL
singstat-2.0.2.dist-info/top_level.txt
singstat-2.0.2.dist-info/RECORD
