Metadata-Version: 2.1
Name: singstat
Version: 2.0.2
Summary: Python package for interacting with APIs available at SingStat.gov.sg
Author-email: Yuhui <yuhuibc@gmail.com>
License:                     GNU GENERAL PUBLIC LICENSE
Project-URL: Homepage, https://github.com/yuhui/singstat
Project-URL: Documentation, https://singstat.readthedocs.io/en/latest/
Project-URL: Repository, https://github.com/yuhui/singstat.git
Project-URL: Bug Tracker, https://github.com/yuhui/singstat/issues
Project-URL: Changelog, https://github.com/yuhui/singstat/blob/master/CHANGELOG.rst
Keywords: singstat,singapore statistics,department of statistics singapore,python,singapore,wrapper
Classifier: Development Status :: 5 - Production/Stable
Classifier: Environment :: Web Environment
Classifier: Intended Audience :: Developers
Classifier: License :: OSI Approved :: GNU General Public License v3 (GPLv3)
Classifier: Natural Language :: English
Classifier: Operating System :: MacOS :: MacOS X
Classifier: Operating System :: Microsoft :: Windows
Classifier: Operating System :: OS Independent
Classifier: Operating System :: POSIX
Classifier: Programming Language :: Python :: 3
Classifier: Topic :: Software Development :: Libraries :: Python Modules
Classifier: Typing :: Typed
Requires-Python: >=3.11
License-File: LICENSE.txt
Requires-Dist: requests
Requires-Dist: requests-cache
Requires-Dist: typeguard
Requires-Dist: types-requests
